pfff/__init__.py
pfff/__main__.py
pfff/cli.py
pfff-1.0.0.dist-info/METADATA
pfff-1.0.0.dist-info/WHEEL
pfff-1.0.0.dist-info/entry_points.txt
pfff-1.0.0.dist-info/RECORD
